setup.py
popular_distributions/Binomialdistribution.py
popular_distributions/Gaussiandistribution.py
popular_distributions/Generaldistribution.py
popular_distributions/__init__.py
popular_distributions.egg-info/PKG-INFO
popular_distributions.egg-info/SOURCES.txt
popular_distributions.egg-info/dependency_links.txt
popular_distributions.egg-info/not-zip-safe
popular_distributions.egg-info/top_level.txt