Metadata-Version: 1.0
Name: popular-distributions
Version: 0.1
Summary: Gaussian and Binomial distributions
Home-page: UNKNOWN
Author: Roman Ivashkin
Author-email: ivashkinrg@gmail.com
License: UNKNOWN
Platform: UNKNOWN
